{"miami-fl": {"name": "Miami FL"}, "florida": {"name": "Florida"}, "arizona": {"name": "Arizona"}, "hawaii": {"name": "Hawai`i"}, "webber-intl": {"name": "Webber Int'l"}, "reinhardt": {"name": "Reinhardt"}, "youngstown-st": {"name": "Youngstown St"}, "samford": {"name": "Samford"}, "alabama-st": {"name": "Alabama St"}, "alabama-birmingham": {"name": "Alabama-Birmingham"}, "kent-st": {"name": "Kent St"}, "arizona-st": {"name": "Arizona St"}, "north-carolina-central": {"name": "North Carolina Central"}, "austin-peay": {"name": "Austin Peay"}, "morgan-st": {"name": "Morgan St"}, "bowling-green": {"name": "Bowling Green"}, "utah": {"name": "Utah"}, "brigham-young": {"name": "Brigham Young"}, "robert-morris-pa": {"name": "Robert Morris PA"}, "buffalo": {"name": "Buffalo"}, "florida-am": {"name": "Florida A&M"}, "central-florida": {"name": "Central Florida"}, "albany-ny": {"name": "Albany NY"}, "central-michigan": {"name": "Central Michigan"}, "eastern-illinois": {"name": "Eastern Illinois"}, "chattanooga": {"name": "Chattanooga"}, "ucla": {"name": "UCLA"}, "cincinnati": {"name": "Cincinnati"}, "georgia-tech": {"name": "Georgia Tech"}, "clemson": {"name": "Clemson"}, "wagner": {"name": "Wagner"}, "connecticut": {"name": "Connecticut"}, "dakota-wesleyan": {"name": "Dakota Wesleyan"}, "dakota-st": {"name": "Dakota St"}, "delaware-st": {"name": "Delaware St"}, "delaware": {"name": "Delaware"}, "rocky-mountain": {"name": "Rocky Mountain"}, "dickinson-st": {"name": "Dickinson St"}, "ottawa-az": {"name": "Ottawa AZ"}, "doane": {"name": "Doane"}, "keiser": {"name": "Keiser"}, "dordt": {"name": "Dordt"}, "valparaiso": {"name": "Valparaiso"}, "eastern-kentucky": {"name": "Eastern Kentucky"}, "midamerica-nazarene": {"name": "MidAmerica Nazarene"}, "grand-view": {"name": "Grand View"}, "bethel-tn": {"name": "Bethel TN"}, "lamar": {"name": "Lamar"}, "campbellsville": {"name": "Campbellsville"}, "lindsey-wilson": {"name": "Lindsey Wilson"}, "south-dakota-st": {"name": "South Dakota St"}, "minnesota": {"name": "Minnesota"}, "union-ky": {"name": "Union KY"}, "morehead-st": {"name": "Morehead St"}, "pikeville": {"name": "Pikeville"}, "murray-st": {"name": "Murray St"}, "western-illinois": {"name": "Western Illinois"}, "north-alabama": {"name": "North Alabama"}, "missouri-st": {"name": "Missouri S&T"}, "northern-arizona": {"name": "Northern Arizona"}, "jacksonville-fl": {"name": "Jacksonville FL"}, "richmond": {"name": "Richmond"}, "northern-colorado": {"name": "Northern Colorado"}, "san-jose-st": {"name": "San Jose St"}, "jacksonville-st": {"name": "Jacksonville St"}, "se-louisiana": {"name": "SE Louisiana"}, "southern-illinois": {"name": "Southern Illinois"}, "se-missouri-st": {"name": "SE Missouri St"}, "bryant": {"name": "Bryant"}, "stony-brook": {"name": "Stony Brook"}, "northwestern-st": {"name": "Northwestern St"}, "tennessee-martin": {"name": "Tennessee-Martin"}, "texas-st-san-marcos": {"name": "Texas St-San Marcos"}, "texas-am": {"name": "Texas A&M"}, "florida-intl": {"name": "Florida Int'l"}, "tulane": {"name": "Tulane"}, "gardner-webb": {"name": "Gardner-Webb"}, "unc-charlotte": {"name": "UNC-Charlotte"}, "jamestown": {"name": "Jamestown"}, "valley-city-st": {"name": "Valley City St"}, "central-arkansas": {"name": "Central Arkansas"}, "western-kentucky": {"name": "Western Kentucky"}, "rice": {"name": "Rice"}, "army": {"name": "Army"}, "colorado-st": {"name": "Colorado St"}, "colorado": {"name": "Colorado"}, "sacred-heart": {"name": "Sacred Heart"}, "maine": {"name": "Maine"}, "tulsa": {"name": "Tulsa"}, "michigan-st": {"name": "Michigan St"}, "purdue": {"name": "Purdue"}, "nevada": {"name": "Nevada"}, "oklahoma-st": {"name": "Oklahoma St"}, "oregon-st": {"name": "Oregon St"}, "massachusetts": {"name": "Massachusetts"}, "rutgers": {"name": "Rutgers"}, "wisconsin": {"name": "Wisconsin"}, "south-florida": {"name": "South Florida"}, "utah-st": {"name": "Utah St"}, "wake-forest": {"name": "Wake Forest"}, "colgate": {"name": "Colgate"}, "air-force": {"name": "Air Force"}, "duke": {"name": "Duke"}, "alabama": {"name": "Alabama"}, "east-tennessee-st": {"name": "East Tennessee St"}, "appalachian-st": {"name": "Appalachian St"}, "montana-st-northern": {"name": "Montana St-Northern"}, "arizona-christian": {"name": "Arizona Christian"}, "portland-st": {"name": "Portland St"}, "arkansas": {"name": "Arkansas"}, "smu": {"name": "SMU"}, "arkansas-st": {"name": "Arkansas St"}, "oregon": {"name": "Oregon"}, "auburn": {"name": "Auburn"}, "stephen-f-austin": {"name": "Stephen F. Austin"}, "baylor": {"name": "Baylor"}, "virginia-tech": {"name": "Virginia Tech"}, "boston-college": {"name": "Boston College"}, "san-diego": {"name": "San Diego"}, "cal-poly-slo": {"name": "Cal Poly SLO"}, "uc-davis": {"name": "UC-Davis"}, "california": {"name": "California"}, "warner-u": {"name": "Warner U."}, "cincinnati-christian-u": {"name": "Cincinnati Christian U."}, "central-methodist": {"name": "Central Methodist"}, "clarke": {"name": "Clarke"}, "eastern-michigan": {"name": "Eastern Michigan"}, "coastal-carolina": {"name": "Coastal Carolina"}, "eastern-oregon": {"name": "Eastern Oregon"}, "coll-of-idaho": {"name": "Coll of Idaho"}, "baker": {"name": "Baker"}, "culver-stockton": {"name": "Culver-Stockton"}, "georgetown-dc": {"name": "Georgetown DC"}, "davidson": {"name": "Davidson"}, "bluefield-va": {"name": "Bluefield VA"}, "faulkner": {"name": "Faulkner"}, "boise-st": {"name": "Boise St"}, "florida-st": {"name": "Florida St"}, "central-conn-st": {"name": "Central Conn St"}, "fordham": {"name": "Fordham"}, "charleston-southern": {"name": "Charleston Southern"}, "furman": {"name": "Furman"}, "benedictine-ks": {"name": "Benedictine KS"}, "graceland": {"name": "Graceland"}, "elizabeth-city-st": {"name": "Elizabeth City St"}, "hampton": {"name": "Hampton"}, "ok-panhandle-st": {"name": "OK Panhandle St"}, "hastings": {"name": "Hastings"}, "akron": {"name": "Akron"}, "illinois": {"name": "Illinois"}, "ball-st": {"name": "Ball St"}, "indiana": {"name": "Indiana"}, "miami-oh": {"name": "Miami OH"}, "iowa": {"name": "Iowa"}, "northern-iowa": {"name": "Northern Iowa"}, "iowa-st": {"name": "Iowa St"}, "indiana-st": {"name": "Indiana St"}, "kansas": {"name": "Kansas"}, "nicholls-st": {"name": "Nicholls St"}, "kansas-st": {"name": "Kansas St"}, "texas-wesleyan": {"name": "Texas Wesleyan"}, "kansas-wesleyan": {"name": "Kansas Wesleyan"}, "point-u": {"name": "Point U."}, "kennesaw-st": {"name": "Kennesaw St"}, "toledo": {"name": "Toledo"}, "kentucky": {"name": "Kentucky"}, "st-francis-pa": {"name": "St Francis PA"}, "lehigh": {"name": "Lehigh"}, "syracuse": {"name": "Syracuse"}, "liberty": {"name": "Liberty"}, "mississippi-st": {"name": "Mississippi St"}, "louisiana-lafayette": {"name": "Louisiana-Lafayette"}, "grambling-st": {"name": "Grambling St"}, "louisiana-monroe": {"name": "Louisiana-Monroe"}, "georgia-southern": {"name": "Georgia Southern"}, "lsu": {"name": "LSU"}, "missouri-baptist": {"name": "Missouri Baptist"}, "lyon": {"name": "Lyon"}, "vmi": {"name": "VMI"}, "marshall": {"name": "Marshall"}, "howard": {"name": "Howard"}, "maryland": {"name": "Maryland"}, "lewis-clark-valley": {"name": "Lewis-Clark Valley"}, "mayville-st": {"name": "Mayville St"}, "southern-u": {"name": "Southern U."}, "mcneese-st": {"name": "McNeese St"}, "mississippi": {"name": "Mississippi"}, "memphis": {"name": "Memphis"}, "virginia-u-lynchburg": {"name": "Virginia U-Lynchburg"}, "merrimack": {"name": "Merrimack"}, "middle-tennessee-st": {"name": "Middle Tennessee St"}, "michigan": {"name": "Michigan"}, "st-francis-il": {"name": "St Francis IL"}, "morningside": {"name": "Morningside"}, "holy-cross": {"name": "Holy Cross"}, "navy": {"name": "Navy"}, "south-alabama": {"name": "South Alabama"}, "nebraska": {"name": "Nebraska"}, "sam-houston-st": {"name": "Sam Houston St"}, "new-mexico": {"name": "New Mexico"}, "elon": {"name": "Elon"}, "north-carolina-at": {"name": "North Carolina A&T"}, "east-carolina": {"name": "East Carolina"}, "north-carolina-st": {"name": "North Carolina St"}, "drake": {"name": "Drake"}, "north-dakota": {"name": "North Dakota"}, "butler": {"name": "Butler"}, "north-dakota-st": {"name": "North Dakota St"}, "abilene-christian": {"name": "Abilene Christian"}, "north-texas": {"name": "North Texas"}, "illinois-st": {"name": "Illinois St"}, "northern-illinois": {"name": "Northern Illinois"}, "florida-atlantic": {"name": "Florida Atlantic"}, "ohio-state": {"name": "Ohio State"}, "rhode-island": {"name": "Rhode Island"}, "ohio-u": {"name": "Ohio U."}, "norfolk-st": {"name": "Norfolk St"}, "old-dominion": {"name": "Old Dominion"}, "idaho": {"name": "Idaho"}, "penn-state": {"name": "Penn State"}, "missouri-valley": {"name": "Missouri Valley"}, "peru-st": {"name": "Peru St"}, "virginia": {"name": "Virginia"}, "pittsburgh": {"name": "Pittsburgh"}, "trinity-intl": {"name": "Trinity Int'l"}, "presentation": {"name": "Presentation"}, "southern-oregon": {"name": "Southern Oregon"}, "sacramento-st": {"name": "Sacramento St"}, "weber-st": {"name": "Weber St"}, "san-diego-st": {"name": "San Diego St"}, "north-carolina": {"name": "North Carolina"}, "south-carolina": {"name": "South Carolina"}, "wofford": {"name": "Wofford"}, "south-carolina-st": {"name": "South Carolina St"}, "montana": {"name": "Montana"}, "south-dakota": {"name": "South Dakota"}, "fresno-st": {"name": "Fresno St"}, "southern-cal": {"name": "Southern Cal"}, "alcorn-st": {"name": "Alcorn St"}, "southern-miss": {"name": "Southern Miss"}, "midland-u": {"name": "Midland U."}, "southwestern-ks": {"name": "Southwestern KS"}, "northwestern": {"name": "northwestern"}, "stanford": {"name": "Stanford"}, "tabor": {"name": "Tabor"}, "sw-assem-of-god": {"name": "SW Assem of God"}, "arkansas-pine-bluff": {"name": "Arkansas-Pine Bluff"}, "tcu": {"name": "TCU"}, "bucknell": {"name": "Bucknell"}, "temple": {"name": "Temple"}, "georgia-st": {"name": "Georgia St"}, "tennessee": {"name": "Tennessee"}, "mississippi-valley-st": {"name": "Mississippi Valley St"}, "tennessee-st": {"name": "Tennessee St"}, "tennessee-tech": {"name": "Tennessee Tech"}, "louisiana-tech": {"name": "Louisiana Tech"}, "texas": {"name": "Texas"}, "prairie-view-am": {"name": "Prairie View A&M"}, "texas-southern": {"name": "Texas Southern"}, "montana-st": {"name": "Montana St"}, "texas-tech": {"name": "Texas Tech"}, "incarnate-word": {"name": "Incarnate Word"}, "texas-san-antonio": {"name": "Texas-San Antonio"}, "towson": {"name": "Towson"}, "the-citadel": {"name": "The Citadel"}, "kentucky-christian": {"name": "Kentucky Christian"}, "thomas-more": {"name": "Thomas More"}, "campbell": {"name": "Campbell"}, "troy": {"name": "Troy"}, "southern-utah": {"name": "Southern Utah"}, "unlv": {"name": "UNLV"}, "houston-baptist": {"name": "Houston Baptist"}, "utep": {"name": "UTEP"}, "georgia": {"name": "Georgia"}, "vanderbilt": {"name": "Vanderbilt"}, "briar-cliff": {"name": "Briar Cliff"}, "waldorf": {"name": "Waldorf"}, "eastern-washington": {"name": "Eastern Washington"}, "washington": {"name": "Washington"}, "new-mexico-st": {"name": "New Mexico St"}, "washington-st": {"name": "Washington St"}, "st-mary-ks": {"name": "St Mary KS"}, "wayland-baptist": {"name": "Wayland Baptist"}, "james-madison": {"name": "James Madison"}, "west-virginia": {"name": "West Virginia"}, "mercer": {"name": "Mercer"}, "western-carolina": {"name": "Western Carolina"}, "monmouth-nj": {"name": "Monmouth NJ"}, "western-michigan": {"name": "Western Michigan"}, "lafayette": {"name": "Lafayette"}, "william-mary": {"name": "William & Mary"}, "evangel": {"name": "Evangel"}, "william-penn": {"name": "William Penn"}, "missouri": {"name": "Missouri"}, "wyoming": {"name": "Wyoming"}, "morehouse": {"name": "Morehouse"}, "alabama-am": {"name": "Alabama A&M"}, "bethune-cookman": {"name": "Bethune-Cookman"}, "jackson-st": {"name": "Jackson St"}, "houston": {"name": "Houston"}, "oklahoma": {"name": "Oklahoma"}, "notre-dame": {"name": "Notre Dame"}, "louisville": {"name": "Louisville"}, "glenville-st": {"name": "Glenville St"}, "alderson-broaddus": {"name": "Alderson Broaddus"}, "western-oregon": {"name": "Western Oregon"}, "angelo-st": {"name": "Angelo St"}, "arkansas-tech": {"name": "Arkansas Tech"}, "arkansas-monticello": {"name": "Arkansas-Monticello"}, "indianapolis": {"name": "Indianapolis"}, "ashland": {"name": "Ashland"}, "west-florida": {"name": "West Florida"}, "carson-newman": {"name": "Carson-Newman"}, "fort-hays-st": {"name": "Fort Hays St"}, "central-missouri": {"name": "Central Missouri"}, "pittsburg-st": {"name": "Pittsburg St"}, "central-oklahoma": {"name": "Central Oklahoma"}, "fairmont-st": {"name": "Fairmont St"}, "charleston-wv": {"name": "Charleston WV"}, "sioux-falls": {"name": "Sioux Falls"}, "concordia-st-paul": {"name": "Concordia-St Paul"}, "tusculum": {"name": "Tusculum"}, "delta-st": {"name": "Delta St"}, "nw-oklahoma-st": {"name": "NW Oklahoma St"}, "east-central-ok": {"name": "East Central OK"}, "northeastern-st-ok": {"name": "Northeastern St OK"}, "emporia-st": {"name": "Emporia St"}, "findlay": {"name": "Findlay"}, "ferris-st": {"name": "Ferris St"}, "west-virginia-st": {"name": "West Virginia St"}, "frostburg-st": {"name": "Frostburg St"}, "buena-vista": {"name": "Buena Vista"}, "hamline": {"name": "Hamline"}, "western-colorado": {"name": "Western Colorado"}, "idaho-st": {"name": "Idaho St"}, "wingate": {"name": "Wingate"}, "johnson-c-smith": {"name": "Johnson C. Smith"}, "lincoln-pa": {"name": "Lincoln PA"}, "lock-haven": {"name": "Lock Haven"}, "trine": {"name": "Trine"}, "manchester": {"name": "Manchester"}, "st-cloud-st": {"name": "St Cloud St"}, "mary": {"name": "Mary"}, "lake-erie": {"name": "Lake Erie"}, "mercyhurst": {"name": "Mercyhurst"}, "belhaven": {"name": "Belhaven"}, "millsaps": {"name": "Millsaps"}, "minn-st-moorhead": {"name": "Minn St-Moorhead"}, "minnesota-crookston": {"name": "Minnesota-Crookston"}, "minot-st": {"name": "Minot St"}, "minnesota-duluth": {"name": "Minnesota-Duluth"}, "nebraska-kearney": {"name": "Nebraska-Kearney"}, "missouri-southern": {"name": "Missouri Southern"}, "nw-missouri-st": {"name": "NW Missouri St"}, "missouri-western": {"name": "Missouri Western"}, "newberry": {"name": "Newberry"}, "north-greenville": {"name": "North Greenville"}, "bemidji-st": {"name": "Bemidji St"}, "northern-st-sd": {"name": "Northern St SD"}, "harding": {"name": "Harding"}, "ouachita-baptist": {"name": "Ouachita Baptist"}, "millersville": {"name": "Millersville"}, "pace": {"name": "Pace"}, "johns-hopkins": {"name": "Johns Hopkins"}, "randolph-macon": {"name": "Randolph-Macon"}, "sw-oklahoma-st": {"name": "SW Oklahoma St"}, "se-oklahoma-st": {"name": "SE Oklahoma St"}, "gannon": {"name": "Gannon"}, "southern-conn-st": {"name": "Southern Conn St"}, "southern-arkansas": {"name": "Southern Arkansas"}, "southern-nazarene": {"name": "Southern Nazarene"}, "mcmurry": {"name": "McMurry"}, "trinity-tx": {"name": "Trinity TX"}, "lincoln-mo": {"name": "Lincoln MO"}, "washburn": {"name": "Washburn"}, "slippery-rock": {"name": "Slippery Rock"}, "wayne-st-mi": {"name": "Wayne St MI"}, "capital": {"name": "Capital"}, "westminster-pa": {"name": "Westminster PA"}, "lake-forest": {"name": "Lake Forest"}, "wisconsin-lutheran": {"name": "Wisconsin Lutheran"}, "salisbury": {"name": "Salisbury"}, "albright": {"name": "Albright"}, "anna-maria": {"name": "Anna Maria"}, "becker": {"name": "Becker"}, "stevenson": {"name": "Stevenson"}, "curry": {"name": "Curry"}, "nichols": {"name": "Nichols"}, "dean": {"name": "Dean"}, "framingham-st": {"name": "Framingham St"}, "endicott": {"name": "Endicott"}, "alvernia": {"name": "Alvernia"}, "gallaudet": {"name": "Gallaudet"}, "delaware-valley": {"name": "Delaware Valley"}, "kean": {"name": "Kean"}, "hope": {"name": "Hope"}, "millikin": {"name": "Millikin"}, "chapman": {"name": "Chapman"}, "pacific-or": {"name": "Pacific OR"}, "california-pa": {"name": "California PA"}, "st-anselm": {"name": "St Anselm"}, "worcester-st": {"name": "Worcester St"}, "wpi": {"name": "WPI"}, "colorado-mines": {"name": "Colorado Mines"}, "adams-st": {"name": "Adams St"}, "heidelberg": {"name": "Heidelberg"}, "adrian": {"name": "Adrian"}, "tuskegee": {"name": "Tuskegee"}, "valdosta-st": {"name": "Valdosta St"}, "albany-st-ga": {"name": "Albany St GA"}, "defiance": {"name": "Defiance"}, "albion": {"name": "Albion"}, "mississippi-college": {"name": "Mississippi College"}, "baldwin-wallace": {"name": "Baldwin Wallace"}, "alma": {"name": "Alma"}, "bowie-st": {"name": "Bowie St"}, "american-intl": {"name": "American Int'l"}, "north-park": {"name": "North Park"}, "anderson": {"name": "Anderson"}, "greensboro": {"name": "Greensboro"}, "apprentice": {"name": "Apprentice"}, "coe": {"name": "Coe"}, "augustana-il": {"name": "Augustana IL"}, "upper-iowa": {"name": "Upper Iowa"}, "augustana-sd": {"name": "Augustana SD"}, "st-norbert": {"name": "St Norbert"}, "aurora": {"name": "Aurora"}, "howard-payne": {"name": "Howard Payne"}, "austin": {"name": "Austin"}, "cumberlands-ky": {"name": "Cumberlands KY"}, "ave-maria": {"name": "Ave Maria"}, "concordia-il": {"name": "Concordia IL"}, "beloit": {"name": "Beloit"}, "franklin": {"name": "Franklin"}, "benedictine-il": {"name": "Benedictine IL"}, "bethany-ks": {"name": "Bethany KS"}, "bethel-ks": {"name": "Bethel KS"}, "simpson": {"name": "Simpson"}, "bethel-mn": {"name": "Bethel MN"}, "chadron-st": {"name": "Chadron St"}, "black-hills-st": {"name": "Black Hills St"}, "stonehill": {"name": "Stonehill"}, "bloomsburg": {"name": "Bloomsburg"}, "morrisville-st": {"name": "Morrisville St"}, "bridgewater-st-ma": {"name": "Bridgewater St MA"}, "gettysburg": {"name": "Gettysburg"}, "bridgewater-va": {"name": "Bridgewater VA"}, "st-john-fisher": {"name": "St John Fisher"}, "buffalo-st": {"name": "Buffalo St"}, "indiana-wesleyan": {"name": "Indiana Wesleyan"}, "shaw": {"name": "Shaw"}, "macalester": {"name": "Macalester"}, "carleton": {"name": "Carleton"}, "plymouth-st": {"name": "Plymouth St"}, "castleton": {"name": "Castleton"}, "west-georgia": {"name": "West Georgia"}, "catawba": {"name": "Catawba"}, "kenyon": {"name": "Kenyon"}, "catholic": {"name": "Catholic"}, "northwestern-mn": {"name": "Northwestern MN"}, "central-ia": {"name": "Central IA"}, "quincy": {"name": "Quincy"}, "central-st-oh": {"name": "Central St OH"}, "washington-mo": {"name": "Washington MO"}, "chicago": {"name": "Chicago"}, "north-central": {"name": "North Central"}, "christopher-newport": {"name": "Christopher Newport"}, "livingstone": {"name": "Livingstone"}, "clark-atlanta": {"name": "Clark Atlanta"}, "concordia-ne": {"name": "Concordia NE"}, "finlandia": {"name": "Finlandia"}, "concordia-wi": {"name": "Concordia WI"}, "iowa-wesleyan": {"name": "Iowa Wesleyan"}, "cornell-ia": {"name": "Cornell IA"}, "fitchburg-st": {"name": "Fitchburg St"}, "cortland-st": {"name": "Cortland St"}, "cumberland-tn": {"name": "Cumberland TN"}, "ohio-northern": {"name": "Ohio Northern"}, "denison": {"name": "Denison"}, "colorado-st-pueblo": {"name": "Colorado St-Pueblo"}, "dixie-st": {"name": "Dixie St"}, "truman-st": {"name": "Truman St"}, "walsh": {"name": "Walsh"}, "duquesne": {"name": "Duquesne"}, "shorter": {"name": "Shorter"}, "eastern-new-mexico": {"name": "Eastern New Mexico"}, "lindenwood": {"name": "Lindenwood"}, "edward-waters": {"name": "Edward Waters"}, "north-carolina-wesleyan": {"name": "North Carolina Wesleyan"}, "emory-henry": {"name": "Emory & Henry"}, "knox": {"name": "Knox"}, "eureka": {"name": "Eureka"}, "benedict": {"name": "Benedict"}, "fayetteville-st": {"name": "Fayetteville St"}, "miles": {"name": "Miles"}, "fort-valley-st": {"name": "Fort Valley St"}, "wesley": {"name": "Wesley"}, "franklin-pierce": {"name": "Franklin Pierce"}, "redlands": {"name": "Redlands"}, "george-fox": {"name": "George Fox"}, "marist": {"name": "Marist"}, "edinboro": {"name": "Edinboro"}, "grand-valley-st": {"name": "Grand Valley St"}, "wartburg": {"name": "Wartburg"}, "greenville": {"name": "Greenville"}, "lawrence": {"name": "Lawrence"}, "grinnell": {"name": "Grinnell"}, "martin-luther": {"name": "Martin Luther"}, "gustavus-adolphus": {"name": "Gustavus Adolphus"}, "averett": {"name": "Averett"}, "hampden-sydney": {"name": "Hampden-Sydney"}, "virginia-union": {"name": "Virginia Union"}, "centre": {"name": "Centre"}, "hanover": {"name": "Hanover"}, "wilkes": {"name": "Wilkes"}, "hartwick": {"name": "Hartwick"}, "hendrix": {"name": "Hendrix"}, "michigan-tech": {"name": "Michigan Tech"}, "hillsdale": {"name": "Hillsdale"}, "marietta": {"name": "Marietta"}, "hiram": {"name": "Hiram"}, "brockport-st": {"name": "Brockport St"}, "hobart": {"name": "Hobart"}, "new-hampshire": {"name": "New Hampshire"}, "guilford": {"name": "Guilford"}, "huntingdon-al": {"name": "Huntingdon AL"}, "central-washington": {"name": "Central Washington"}, "rhodes": {"name": "Rhodes"}, "illinois-college": {"name": "Illinois College"}, "new-haven": {"name": "New Haven"}, "indiana-pa": {"name": "Indiana PA"}, "dayton": {"name": "Dayton"}, "uw-stevens-point": {"name": "UW-Stevens Point"}, "john-carroll": {"name": "John Carroll"}, "grove-city": {"name": "Grove City"}, "juniata": {"name": "Juniata"}, "georgetown-ky": {"name": "Georgetown KY"}, "concordia-mi": {"name": "Concordia MI"}, "kentucky-wesleyan": {"name": "Kentucky Wesleyan"}, "moravian": {"name": "Moravian"}, "kings-pa": {"name": "King's PA"}, "assumption": {"name": "Assumption"}, "kutztown": {"name": "Kutztown"}, "whitworth": {"name": "Whitworth"}, "la-verne": {"name": "La Verne"}, "birmingham-southern": {"name": "Birmingham-Southern"}, "lagrange": {"name": "LaGrange"}, "carroll-wi": {"name": "Carroll WI"}, "lakeland": {"name": "Lakeland"}, "st-xavier": {"name": "St Xavier"}, "lawrence-tech": {"name": "Lawrence Tech"}, "franklin-marshall": {"name": "Franklin & Marshall"}, "lebanon-valley": {"name": "Lebanon Valley"}, "st-augustines": {"name": "St Augustine's"}, "lenoir-rhyne": {"name": "Lenoir-Rhyne"}, "pomona-pitzer": {"name": "Pomona-Pitzer"}, "rockford": {"name": "Rockford"}, "macmurray": {"name": "MacMurray"}, "berry": {"name": "Berry"}, "maryville-tn": {"name": "Maryville TN"}, "misericordia": {"name": "Misericordia"}, "mcdaniel": {"name": "McDaniel"}, "langston": {"name": "Langston"}, "mcpherson": {"name": "McPherson"}, "fdu-florham": {"name": "FDU-Florham"}, "merchant-marine": {"name": "Merchant Marine"}, "uw-river-falls": {"name": "UW-River Falls"}, "minnesota-morris": {"name": "Minnesota-Morris"}, "st-ambrose": {"name": "St Ambrose"}, "carnegie-mellon": {"name": "Carnegie Mellon"}, "mit": {"name": "MIT"}, "wheaton": {"name": "Wheaton"}, "monmouth-il": {"name": "Monmouth IL"}, "montana-tech": {"name": "Montana Tech"}, "carroll-mt": {"name": "Carroll MT"}, "montana-western": {"name": "Montana-Western"}, "geneva": {"name": "Geneva"}, "mt-st-joseph": {"name": "Mt St Joseph"}, "new-jersey": {"name": "New Jersey"}, "muhlenberg": {"name": "Muhlenberg"}, "waynesburg": {"name": "Waynesburg"}, "muskingum": {"name": "Muskingum"}, "westminster-mo": {"name": "Westminster MO"}, "nebraska-wesleyan": {"name": "Nebraska Wesleyan"}, "virginia-st": {"name": "Virginia St"}, "mckendree": {"name": "McKendree"}, "northern-michigan": {"name": "Northern Michigan"}, "northwestern-ia": {"name": "Northwestern IA"}, "midwestern-st": {"name": "Midwestern St"}, "tiffin": {"name": "Tiffin"}, "northwood": {"name": "Northwood"}, "concord": {"name": "Concord"}, "notre-dame-oh": {"name": "Notre Dame OH"}, "kalamazoo": {"name": "Kalamazoo"}, "oberlin": {"name": "Oberlin"}, "otterbein": {"name": "Otterbein"}, "ohio-wesleyan": {"name": "Ohio Wesleyan"}, "henderson-st": {"name": "Henderson St"}, "oklahoma-baptist": {"name": "Oklahoma Baptist"}, "western-new-mexico": {"name": "Western New Mexico"}, "simon-fraser": {"name": "Simon Fraser"}, "presbyterian": {"name": "Presbyterian"}, "claremont-mudd-scripps": {"name": "Claremont-Mudd-Scripps"}, "puget-sound": {"name": "Puget Sound"}, "augsburg": {"name": "Augsburg"}, "ripon": {"name": "Ripon"}, "taylor": {"name": "Taylor"}, "robert-morris-il": {"name": "Robert Morris IL"}, "kentucky-st": {"name": "Kentucky St"}, "case-western-reserve": {"name": "Case Western Reserve"}, "rochester": {"name": "Rochester"}, "mount-union": {"name": "Mount Union"}, "rose-hulman": {"name": "Rose-Hulman"}, "widener": {"name": "Widener"}, "rowan": {"name": "Rowan"}, "allegheny": {"name": "Allegheny"}, "rpi": {"name": "RPI"}, "norwich": {"name": "Norwich"}, "salve-regina": {"name": "Salve Regina"}, "southwestern-tx": {"name": "Southwestern TX"}, "sewanee": {"name": "Sewanee"}, "ohio-dominican": {"name": "Ohio Dominican"}, "shepherd": {"name": "Shepherd"}, "clarion": {"name": "Clarion"}, "shippensburg": {"name": "Shippensburg"}, "olivet-nazarene": {"name": "Olivet Nazarene"}, "siena-heights": {"name": "Siena Heights"}, "lane": {"name": "Lane"}, "liu": {"name": "LIU"}, "colorado-mesa": {"name": "Colorado Mesa"}, "south-dakota-tech": {"name": "South Dakota Tech"}, "montclair-st": {"name": "Montclair St"}, "southern-virginia": {"name": "Southern Virginia"}, "ottawa-ks": {"name": "Ottawa KS"}, "st-francis-in": {"name": "St Francis IN"}, "friends": {"name": "Friends"}, "crown": {"name": "Crown"}, "st-olaf": {"name": "St Olaf"}, "st-scholastica": {"name": "St Scholastica"}, "st-thomas-fl": {"name": "St Thomas FL"}, "st-thomas-mn": {"name": "St Thomas MN"}, "ithaca": {"name": "Ithaca"}, "st-vincent": {"name": "St Vincent"}, "tarleton-st": {"name": "Tarleton St"}, "avila": {"name": "Avila"}, "sterling": {"name": "Sterling"}, "louisiana-college": {"name": "Louisiana College"}, "stetson": {"name": "Stetson"}, "hardin-simmons": {"name": "Hardin-Simmons"}, "sul-ross-st": {"name": "Sul Ross St"}, "maine-maritime": {"name": "Maine Maritime"}, "suny-maritime": {"name": "SUNY-Maritime"}, "lycoming": {"name": "Lycoming"}, "susquehanna": {"name": "Susquehanna"}, "minn-st-mankato": {"name": "Minn St-Mankato"}, "sw-minnesota-st": {"name": "SW Minnesota St"}, "saginaw-valley-st": {"name": "Saginaw Valley St"}, "tamu-kingsville": {"name": "TAMU-Kingsville"}, "texas-permian-basin": {"name": "Texas-Permian Basin"}, "alfred": {"name": "Alfred"}, "thiel": {"name": "Thiel"}, "coast-guard": {"name": "Coast Guard"}, "u-of-new-england": {"name": "U of New England"}, "alfred-st": {"name": "Alfred St"}, "umass-dartmouth": {"name": "UMass-Dartmouth"}, "winston-salem-st": {"name": "Winston-Salem St"}, "unc-pembroke": {"name": "UNC-Pembroke"}, "westfield-st": {"name": "Westfield St"}, "union-ny": {"name": "Union NY"}, "bethany-wv": {"name": "Bethany WV"}, "ursinus": {"name": "Ursinus"}, "st-lawrence": {"name": "St Lawrence"}, "utica": {"name": "Utica"}, "loras": {"name": "Loras"}, "uw-eau-claire": {"name": "UW-Eau Claire"}, "concordia-moorhead": {"name": "Concordia-Moorhead"}, "uw-la-crosse": {"name": "UW-La Crosse"}, "carthage": {"name": "Carthage"}, "uw-oshkosh": {"name": "UW-Oshkosh"}, "east-texas-baptist": {"name": "East Texas Baptist"}, "uw-platteville": {"name": "UW-Platteville"}, "st-johns-mn": {"name": "St John's MN"}, "uw-stout": {"name": "UW-Stout"}, "dubuque": {"name": "Dubuque"}, "uw-whitewater": {"name": "UW-Whitewater"}, "villanova": {"name": "Villanova"}, "chowan": {"name": "Chowan"}, "virginia-wise": {"name": "Virginia-Wise"}, "mars-hill": {"name": "Mars Hill"}, "east-stroudsburg": {"name": "East Stroudsburg"}, "wittenberg": {"name": "Wittenberg"}, "wash-jeff": {"name": "Wash & Jeff"}, "dickinson": {"name": "Dickinson"}, "washington-and-lee": {"name": "Washington and Lee"}, "limestone": {"name": "Limestone"}, "west-alabama": {"name": "West Alabama"}, "bentley": {"name": "Bentley"}, "west-chester": {"name": "West Chester"}, "azusa-pacific": {"name": "Azusa Pacific"}, "west-texas-am": {"name": "West Texas A&M"}, "springfield": {"name": "Springfield"}, "western-new-england": {"name": "Western New England"}, "west-liberty": {"name": "West Liberty"}, "wheeling-jesuit": {"name": "Wheeling Jesuit"}, "luther": {"name": "Luther"}, "whittier": {"name": "Whittier"}, "sw-baptist": {"name": "SW Baptist"}, "william-jewell": {"name": "William Jewell"}, "western-conn-st": {"name": "Western Conn St"}, "william-paterson": {"name": "William Paterson"}, "olivet": {"name": "Olivet"}, "wilmington": {"name": "Wilmington"}, "wayne-st-ne": {"name": "Wayne St NE"}, "winona-st": {"name": "Winona St"}, "bluffton": {"name": "Bluffton"}, "wooster": {"name": "Wooster"}, "urbana": {"name": "Urbana"}, "wv-wesleyan": {"name": "WV Wesleyan"}, "florida-tech": {"name": "Florida Tech"}, "savannah-st": {"name": "Savannah St"}, "st-andrews": {"name": "St Andrews"}, "mass-maritime": {"name": "Mass Maritime"}, "new-mexico-highlands": {"name": "New Mexico Highlands"}, "allen": {"name": "Allen"}, "bates": {"name": "Bates"}, "amherst": {"name": "Amherst"}, "hamilton": {"name": "Hamilton"}, "bowdoin": {"name": "Bowdoin"}, "depauw": {"name": "DePauw"}, "elmhurst": {"name": "Elmhurst"}, "fort-lewis": {"name": "Fort Lewis"}, "ferrum": {"name": "Ferrum"}, "willamette": {"name": "Willamette"}, "davenport": {"name": "Davenport"}, "marian-in": {"name": "Marian IN"}, "mary-hardin-baylor": {"name": "Mary Hardin-Baylor"}, "trinity-bible": {"name": "Trinity Bible"}, "methodist": {"name": "Methodist"}, "williams": {"name": "Williams"}, "middlebury": {"name": "Middlebury"}, "shenandoah": {"name": "Shenandoah"}, "cal-lutheran": {"name": "Cal Lutheran"}, "pacific-lutheran": {"name": "Pacific Lutheran"}, "southeastern-fl": {"name": "Southeastern FL"}, "lewis-clark-or": {"name": "Lewis & Clark OR"}, "linfield": {"name": "Linfield"}, "seton-hill": {"name": "Seton Hill"}, "texas-college": {"name": "Texas College"}, "texas-lutheran": {"name": "Texas Lutheran"}, "trinity-ct": {"name": "Trinity CT"}, "tufts": {"name": "Tufts"}, "husson": {"name": "Husson"}, "illinois-wesleyan": {"name": "Illinois Wesleyan"}, "wabash": {"name": "Wabash"}, "colby": {"name": "Colby"}, "wesleyan": {"name": "Wesleyan"}, "tamu-commerce": {"name": "TAMU-Commerce"}, "brevard": {"name": "Brevard"}, "brown": {"name": "Brown"}, "pennsylvania": {"name": "Pennsylvania"}, "dartmouth": {"name": "Dartmouth"}, "cornell-ny": {"name": "Cornell NY"}, "princeton": {"name": "Princeton"}, "harvard": {"name": "Harvard"}, "columbia": {"name": "Columbia"}, "occidental": {"name": "Occidental"}, "yale": {"name": "Yale"}, "florida-intll": {"name": "Florida Int'll"}}